pyplayingcards/__init__.py
pyplayingcards/playingcards.py
pyplayingcards-1.2.4.dist-info/METADATA
pyplayingcards-1.2.4.dist-info/WHEEL
pyplayingcards-1.2.4.dist-info/top_level.txt
pyplayingcards-1.2.4.dist-info/RECORD
