Metadata-Version: 2.1
Name: pyplayingcards
Version: 1.2.4
Summary: Create and manipulate playing cards in Python!
Home-page: https://github.com/DaJodhi/pyplayingcards
Author: Jodhviir Sekhon
Author-email: jodhsekh07@gmail.com
License: MIT
Platform: UNKNOWN
Classifier: License :: OSI Approved :: MIT License
Classifier: Programming Language :: Python :: 3
Classifier: Programming Language :: Python :: 3.7
